jarvis_tasks_library/__init__.py
jarvis_tasks_library/models.py
jarvis_tasks_library/py.typed
jarvis_tasks_library/tasks.py
jarvis_tasks_library-2.9.0.dist-info/WHEEL
jarvis_tasks_library-2.9.0.dist-info/METADATA
jarvis_tasks_library-2.9.0.dist-info/RECORD
