Metadata-Version: 2.1
Name: jarvis-tasks-library
Version: 2.9.0
Summary: 
Author: Juan Rodriguez
Author-email: angel.neb@gmail.com
Requires-Python: >=3.10,<4.0
Classifier: Programming Language :: Python :: 3
Classifier: Programming Language :: Python :: 3.10
Requires-Dist: pydantic (>=1.10.2,<2.0.0)
Requires-Dist: python-dateutil (>=2.8.2,<3.0.0)
Requires-Dist: types-python-dateutil (>=2.8.19,<3.0.0)
